odoo/addons/base_model_restrict_update/README.rst
odoo/addons/base_model_restrict_update/__init__.py
odoo/addons/base_model_restrict_update/__manifest__.py
odoo/addons/base_model_restrict_update/data/config_parameter_data.xml
odoo/addons/base_model_restrict_update/i18n/base_model_restrict_update.pot
odoo/addons/base_model_restrict_update/i18n/es.po
odoo/addons/base_model_restrict_update/i18n/es_AR.po
odoo/addons/base_model_restrict_update/i18n/it.po
odoo/addons/base_model_restrict_update/i18n/ja_JP.po
odoo/addons/base_model_restrict_update/models/__init__.py
odoo/addons/base_model_restrict_update/models/ir_model.py
odoo/addons/base_model_restrict_update/models/ir_model_access.py
odoo/addons/base_model_restrict_update/models/res_config_settings.py
odoo/addons/base_model_restrict_update/models/res_users.py
odoo/addons/base_model_restrict_update/readme/CONFIGURE.md
odoo/addons/base_model_restrict_update/readme/CONTRIBUTORS.md
odoo/addons/base_model_restrict_update/readme/CREDITS.md
odoo/addons/base_model_restrict_update/readme/DESCRIPTION.md
odoo/addons/base_model_restrict_update/static/description/icon.png
odoo/addons/base_model_restrict_update/static/description/index.html
odoo/addons/base_model_restrict_update/tests/__init__.py
odoo/addons/base_model_restrict_update/tests/test_base_model_restrict_update.py
odoo/addons/base_model_restrict_update/views/ir_model_views.xml
odoo/addons/base_model_restrict_update/views/res_config_settings.xml
odoo/addons/base_model_restrict_update/views/res_users_views.xml
odoo_addon_base_model_restrict_update-18.0.1.0.0.4.dist-info/METADATA
odoo_addon_base_model_restrict_update-18.0.1.0.0.4.dist-info/WHEEL
odoo_addon_base_model_restrict_update-18.0.1.0.0.4.dist-info/top_level.txt
odoo_addon_base_model_restrict_update-18.0.1.0.0.4.dist-info/RECORD
