Metadata-Version: 2.1
Name: odoo-addon-base_model_restrict_update
Version: 18.0.1.0.0.4
Requires-Python: >=3.10
Requires-Dist: odoo==18.0.*
Summary: Update Restrict Model
Home-page: https://github.com/OCA/server-tools
License: LGPL-3
Author: Odoo Community Association (OCA), Quartile
Author-email: support@odoo-community.org
Classifier: Programming Language :: Python
Classifier: Framework :: Odoo
Classifier: Framework :: Odoo :: 18.0
Classifier: License :: OSI Approved :: GNU Lesser General Public License v3 (LGPLv3)
